freestyle_hid/__init__.py
freestyle_hid/_exceptions.py
freestyle_hid/_freestyle_encryption.py
freestyle_hid/_hidwrapper.py
freestyle_hid/_session.py
freestyle_hid/py.typed
freestyle_hid/tests/__init__.py
freestyle_hid/tests/test_freestyle.py
freestyle_hid/tools/__init__.py
freestyle_hid/tools/encrypted_setup_extractor.py
freestyle_hid/tools/extract_chatter.py
freestyle_hid/tools/hid_console.py
freestyle_hid/tools/py.typed
freestyle_hid-1.1.1.dist-info/0BSD.txt
freestyle_hid-1.1.1.dist-info/AUTHORS
freestyle_hid-1.1.1.dist-info/Apache-2.0.txt
freestyle_hid-1.1.1.dist-info/LICENSE
freestyle_hid-1.1.1.dist-info/METADATA
freestyle_hid-1.1.1.dist-info/MIT.txt
freestyle_hid-1.1.1.dist-info/WHEEL
freestyle_hid-1.1.1.dist-info/entry_points.txt
freestyle_hid-1.1.1.dist-info/top_level.txt
freestyle_hid-1.1.1.dist-info/RECORD
