Metadata-Version: 2.1
Name: freestyle-hid
Version: 1.1.1
Summary: Python implementation of the HID protocol used by Abbott FreeStyle devices
Home-page: https://github.com/glucometers-tech/freestyle-hid
Author: Diego Elio Pettenò
Author-email: flameeyes@flameeyes.com
License: Apache-2.0
Keywords: glucometer,diabetes,freestyle,abbott
Classifier: Development Status :: 4 - Beta
Classifier: Environment :: Console
Classifier: Intended Audience :: Developers
Classifier: Intended Audience :: Developers
Classifier: License :: OSI Approved :: Apache Software License
Classifier: Operating System :: OS Independent
Classifier: Programming Language :: Python
Classifier: Programming Language :: Python :: 3
Classifier: Topic :: Scientific/Engineering :: Medical Science Apps.
Requires-Python: ~=3.9
License-File: AUTHORS
License-File: LICENSE
License-File: LICENSES/0BSD.txt
License-File: LICENSES/Apache-2.0.txt
License-File: LICENSES/MIT.txt
Requires-Dist: construct
Provides-Extra: dev
Requires-Dist: mypy ; extra == 'dev'
Requires-Dist: pre-commit ; extra == 'dev'
Requires-Dist: pytest-mypy ; extra == 'dev'
Requires-Dist: pytest-timeout (>=1.3.0) ; extra == 'dev'
Requires-Dist: pytest (>=6.0) ; extra == 'dev'
Requires-Dist: setuptools-scm ; extra == 'dev'
Provides-Extra: encryption
Requires-Dist: freestyle-keys ; extra == 'encryption'
Provides-Extra: hidapi
Requires-Dist: hidapi ; extra == 'hidapi'
Provides-Extra: tools
Requires-Dist: click ; extra == 'tools'
Requires-Dist: click-log ; extra == 'tools'
Requires-Dist: usbmon-tools (~=3.0) ; extra == 'tools'
